AUTHORS.rst
CHANGES.rst
COPYING.LGPLv3
MANIFEST.in
README.rst
setup.py
django_smart_extends.egg-info/PKG-INFO
django_smart_extends.egg-info/SOURCES.txt
django_smart_extends.egg-info/dependency_links.txt
django_smart_extends.egg-info/not-zip-safe
django_smart_extends.egg-info/top_level.txt
smartextends/__init__.py
smartextends/models.py
smartextends/views.py
smartextends/templatetags/__init__.py
smartextends/templatetags/smart_extends_tags.py