Metadata-Version: 1.1
Name: django-smart-extends
Version: 0.7.0
Summary: This application is useful when you want to overwrite a template of a application in your project. Currently this in Django produce infinite recursion 
Home-page: https://github.com/goinnn/django-smart-extends
Author: Pablo Martin
Author-email: goinnn@gmail.com
License: LGPL 3
Keywords: django,extends,infinite recursion,smart extends
Platform: UNKNOWN
Classifier: Development Status :: 4 - Beta
Classifier: Framework :: Django
Classifier: License :: OSI Approved :: GNU Library or Lesser General Public License (LGPL)
